[
  {
    "line": 1,
    "elements": [
      {
        "comments": [
          {
            "line": 4,
            "value": "#without Examples Keyword"
          }
        ],
        "before": [
          {
            "result": {
              "duration": 377700,
              "status": "passed"
            },
            "match": {
              "location": "TaggedHooksStepDefinition.setUP()"
            }
          },
          {
            "result": {
              "duration": 165100,
              "status": "passed"
            },
            "match": {
              "location": "TaggedHooksStepDefinition.setUP1()"
            }
          }
        ],
        "line": 5,
        "name": "Amazon Login Test Scenario",
        "description": "",
        "id": "amazon-login-feature;amazon-login-test-scenario",
        "after": [
          {
            "result": {
              "duration": 1028700,
              "status": "passed"
            },
            "match": {
              "location": "TaggedHooksStepDefinition.tearDown1()"
            }
          },
          {
            "result": {
              "duration": 467800,
              "status": "passed"
            },
            "match": {
              "location": "TaggedHooksStepDefinition.tearDown()"
            }
          }
        ],
        "type": "scenario",
        "keyword": "Scenario",
        "steps": [
          {
            "result": {
              "duration": 199003034700,
              "status": "passed"
            },
            "line": 7,
            "name": "user is in Shopping page",
            "match": {
              "location": "LoginStepDefinition.user_already_on_login_page()"
            },
            "keyword": "Given "
          },
          {
            "result": {
              "duration": 113582600,
              "error_message": "junit.framework.ComparisonFailure: expected:\u003c[Online Shopping site in India: Shop Online for Mobiles, Books, Watches, Shoes and More - A]mazon.in\u003e but was:\u003c[www.a]mazon.in\u003e\r\n\tat junit.framework.Assert.assertEquals(Assert.java:100)\r\n\tat junit.framework.Assert.assertEquals(Assert.java:107)\r\n\tat stepDefinitions.LoginStepDefinition.title_of_login_page_is_free_CRM(LoginStepDefinition.java:39)\r\n\tat ✽.When title of Amazon login page(C:/Users/lenovo/eclipse-workspace/ProjectTest/src/main/java/Features/login.feature:8)\r\n",
              "status": "failed"
            },
            "line": 8,
            "name": "title of Amazon login page",
            "match": {
              "location": "LoginStepDefinition.title_of_login_page_is_free_CRM()"
            },
            "keyword": "When "
          },
          {
            "result": {
              "status": "skipped"
            },
            "line": 9,
            "name": "user clicks on Sign-In Button",
            "match": {
              "location": "LoginStepDefinition.user_click_on_SignIn_Button()"
            },
            "keyword": "Then "
          }
        ]
      }
    ],
    "name": "Amazon Login Feature",
    "description": "",
    "id": "amazon-login-feature",
    "keyword": "Feature",
    "uri": "C:/Users/lenovo/eclipse-workspace/ProjectTest/src/main/java/Features/login.feature"
  }
]